README.md
setup.py
modulojordan/__init__.py
modulojordan/cal.py
modulojordan/caling.py
modulojordan.egg-info/PKG-INFO
modulojordan.egg-info/SOURCES.txt
modulojordan.egg-info/dependency_links.txt
modulojordan.egg-info/top_level.txt