Metadata-Version: 2.1
Name: modulojordan
Version: 0.0.1
Summary: esta es la descripcion de mi paquete
Author: jordan_sion
Author-email: yordansioncossiofuentes@gamil.com
License: MIT
